Metadata-Version: 1.2
Name: objpersist
Version: 0.0.7
Summary: Save (and restore) complicated classes to (and from) a file
Home-page: https://github.com/fergalm/persist
Author: Fergal Mullally
Author-email: fergal.mullally@gmail.com
License: UNKNOWN
Platform: UNKNOWN
Requires-Python: >=3.6
